dash_spread_grid/DashSpreadGrid.py
dash_spread_grid/__init__.py
dash_spread_grid/_imports_.py
dash_spread_grid/dash_spread_grid.min.js
dash_spread_grid/dash_spread_grid.min.js.map
dash_spread_grid/metadata.json
dash_spread_grid/package-info.json
dash_spread_grid-1.0.0.dist-info/licenses/LICENSE
dash_spread_grid-1.0.0.dist-info/METADATA
dash_spread_grid-1.0.0.dist-info/WHEEL
dash_spread_grid-1.0.0.dist-info/top_level.txt
dash_spread_grid-1.0.0.dist-info/RECORD
