Metadata-Version: 2.4
Name: dash_spread_grid
Version: 1.0.0
Summary: Fast grid for Dash applications
Author: Tomasz Rewak <tomasz.rewak@gmail.com>
License: MIT
Classifier: Framework :: Dash
License-File: LICENSE
Dynamic: author
Dynamic: classifier
Dynamic: license
Dynamic: license-file
Dynamic: summary
